CHANGES.txt
CONTRIBUTORS.txt
MANIFEST.in
README.txt
setup.cfg
setup.py
docs/HISTORY.txt
docs/INSTALL.txt
docs/LICENSE.GPL
docs/LICENSE.txt
vs/__init__.py
vs.contentpopup.egg-info/PKG-INFO
vs.contentpopup.egg-info/SOURCES.txt
vs.contentpopup.egg-info/dependency_links.txt
vs.contentpopup.egg-info/entry_points.txt
vs.contentpopup.egg-info/namespace_packages.txt
vs.contentpopup.egg-info/not-zip-safe
vs.contentpopup.egg-info/paster_plugins.txt
vs.contentpopup.egg-info/requires.txt
vs.contentpopup.egg-info/top_level.txt
vs/contentpopup/README.txt
vs/contentpopup/__init__.py
vs/contentpopup/config.py
vs/contentpopup/configure.zcml
vs/contentpopup/header.txt
vs/contentpopup/browser/__init__.py
vs/contentpopup/browser/configure.zcml
vs/contentpopup/browser/image.py
vs/contentpopup/browser/image_overlay.pt
vs/contentpopup/browser/image_overlay2.pt
vs/contentpopup/browser/tables.py
vs/contentpopup/browser/resources/contentpopup.js
vs/contentpopup/content/__init__.py
vs/contentpopup/content/configure.zcml
vs/contentpopup/interfaces/__init__.py
vs/contentpopup/locales/de/LC_MESSAGES/plone.tinymce.po
vs/contentpopup/locales/de/LC_MESSAGES/vs.contentpopup.mo
vs/contentpopup/locales/de/LC_MESSAGES/vs.contentpopup.po
vs/contentpopup/portlets/__init__.py
vs/contentpopup/portlets/configure.zcml
vs/contentpopup/profiles/default/factorytool.xml
vs/contentpopup/profiles/default/jsregistry.xml
vs/contentpopup/profiles/default/metadata.xml
vs/contentpopup/profiles/default/portlets.xml
vs/contentpopup/profiles/default/tinymce.xml
vs/contentpopup/profiles/default/types.xml
vs/contentpopup/subscribers/__init__.py
vs/contentpopup/subscribers/all.py
vs/contentpopup/subscribers/configure.zcml
vs/contentpopup/subscribers/transformation.py
vs/contentpopup/tests/__init__.py
vs/contentpopup/tests/base.py
vs/contentpopup/tests/test_doctest.py