Metadata-Version: 1.0
Name: vs.contentpopup
Version: 0.2.4
Summary: vs.contentpopup
Home-page: http://pypi.python.org/pypi/vs.contentpopup
Author: Andreas Jung
Author-email: info@zopyx.com
License: GPL
Keywords: Plone overlay popup
Platform: UNKNOWN
Classifier: Framework :: Plone
Classifier: Framework :: Plone :: 4.0
Classifier: Framework :: Plone :: 4.1
Classifier: Framework :: Plone :: 4.2
Classifier: Intended Audience :: Developers
Classifier: License :: OSI Approved :: GNU General Public License (GPL)
